Statfigs/__init__.py
statfigs-1.5.7.dist-info/LICENCE.txt
statfigs-1.5.7.dist-info/METADATA
statfigs-1.5.7.dist-info/WHEEL
statfigs-1.5.7.dist-info/top_level.txt
statfigs-1.5.7.dist-info/RECORD
