Metadata-Version: 2.1
Name: statfigs
Version: 1.5.7
Summary: Provides statistics and graphs with significance annotations for scientific publishing
Home-page: UNKNOWN
Author: Jemma Rezitis
Author-email: jemma.rezitis@hotmail.com
License: UNKNOWN
Platform: UNKNOWN
Classifier: Programming Language :: Python :: 3
Classifier: License :: OSI Approved :: MIT License
Classifier: Operating System :: OS Independent
License-File: LICENCE.txt
